project_rigor-0.5.dist-info/licenses/LICENSE
rigor/__init__.py
rigor/app.py
rigor/const.py
rigor/content.py
rigor/display.py
rigor/display_update.py
rigor/encoder.py
rigor/input_handler.py
rigor/module.py
rigor/mqtt_client.py
rigor/renderer.py
rigor/timer.py
rigor/screens/__init__.py
rigor/screens/auto_refresh_screen.py
rigor/screens/input_number.py
rigor/screens/menu_screen.py
rigor/screens/screen.py
rigor/screens/timed_screen.py
project_rigor-0.5.dist-info/METADATA
project_rigor-0.5.dist-info/WHEEL
project_rigor-0.5.dist-info/top_level.txt
project_rigor-0.5.dist-info/RECORD
