Metadata-Version: 2.4
Name: project-rigor
Version: 0.5
Summary: Project RIGOR - The Remote IGOR
Author: jarvick257
License-Expression: MIT
Project-URL: Homepage, https://github.com/jarvick257/rigor
Classifier: Programming Language :: Python :: 3
Classifier: Operating System :: OS Independent
Requires-Python: >=3.9
License-File: LICENSE
Requires-Dist: loguru
Requires-Dist: paho-mqtt
Dynamic: license-file
